{
  "objects": [
    {
      "name": "walk_2",
      "type": "Sprite",
      "texture": "walk",
      "x": 702,
      "y": 1068,
      "depth": 0,
      "scaleX": 1,
      "scaleY": 1,
      "angle": 0,
      "alpha": 1,
      "group": "player",
      "events": [
        {
          "trigger": "onDirectionChange",
          "actions": "[set_flip_x value=true]",
          "condition": "direction === 'left'"
        },
        {
          "trigger": "onDirectionChange",
          "actions": "[set_flip_x value=false]",
          "condition": "direction === 'right'"
        },
        {
          "trigger": "onStateChange",
          "actions": "[anim_play name=歩き]",
          "condition": "state === 'walk'"
        },
        {
          "trigger": "onStateChange",
          "actions": "[anim_stop]",
          "condition": "state === 'idle'"
        },
        {
          "trigger": "onStateChange",
          "actions": "[anim_frame name=歩き frame=0]",
          "condition": "state === 'idle'"
        }
      ],
      "components": [
        {
          "type": "PlayerController",
          "params": {}
        }
      ],
      "physics": {
        "isStatic": false,
        "ignoreGravity": false,
        "gravityScale": 1,
        "shape": "rectangle",
        "friction": 0.1,
        "restitution": 0
      }
    }
    
  ],
  "animations": [
    {
      "key": "歩き",
      "texture": "walk",
      "frames": {
        "start": 0,
        "end": 4
      },
      "frameRate": 10,
      "repeat": -1
    }
  ]
}